setup.py
transmission/__init__.py
transmission/__version__.py
transmission/events.py
transmission/exceptions.py
transmission/signals.py
transmission/transitions.py
transmission/utils.py
transmission.egg-info/PKG-INFO
transmission.egg-info/SOURCES.txt
transmission.egg-info/dependency_links.txt
transmission.egg-info/requires.txt
transmission.egg-info/top_level.txt