Metadata-Version: 1.1
Name: transmission
Version: 1.4.1
Summary: Transmission is a utility package that houses decorators and signals pertaining to state transitions and generalized events
Home-page: https://github.com/hangarunderground/transmission
Author: hangarunderground
Author-email: transmission@reelio.com
License: UNKNOWN
Download-URL: https://github.com/hangarunderground/transmission/tarball/1.4.1
Keywords: django,finite state machine,rest,signals
Platform: UNKNOWN
Classifier: Development Status :: 4 - Beta
Classifier: Framework :: Django
Classifier: Intended Audience :: Developers
Classifier: License :: OSI Approved :: MIT License
Classifier: Operating System :: POSIX
Classifier: Programming Language :: Python
Classifier: Topic :: Internet :: WWW/HTTP
